{
  "environment": "production",
  "api": {
    "baseUrl": "https://api.example.com",
    "licenseEndpoint": "https://api.example.com/license",
    "analyticsEndpoint": "https://api.example.com/analytics",
    "timeout": 10000
  },
  "features": {
    "enableBetaFeatures": false,
    "enableDebugMode": false,
    "enableTelemetry": true,
    "enableAutoUpdate": true
  },
  "logging": {
    "level": "warn",
    "console": false,
    "remote": true
  },
  "rateLimit": {
    "requestsPerMinute": 60,
    "burstSize": 10
  }
}
